[
    {
        "pk": 727359, 
        "model": "collection.museumobject", 
        "fields": {
            "original_price": "", 
            "attributions_note": "", 
            "related_museum_numbers": "", 
            "museum_number": "E.1113-1920", 
            "date_end": "1892-12-31", 
            "labels": [], 
            "descriptive_line": "Design for needlepoint lace. Made up in the Convent of the Poor Clares, Kenmare, Ireland, c.1888", 
            "shape": "", 
            "longitude": "-9.58384000", 
            "year_start": 1883, 
            "exhibitions": [], 
            "subjects": [], 
            "date_text": "c.1888", 
            "primary_image_id": "", 
            "rights": 2, 
            "physical_description": "Design for flat needlepoint lace", 
            "dimensions": "Height: 103 mm, Width: 346 mm", 
            "title": "", 
            "date_start": "1883-01-01", 
            "materials_techniques": "chinese white", 
            "last_processed": "2014-04-26 18:56:33", 
            "label": "", 
            "event_text": "", 
            "production_type": "", 
            "collections": [
                {
                    "pk": 1, 
                    "model": "collection.collection", 
                    "fields": {
                        "code": "PDP", 
                        "name": "Prints, Drawings and Paintings Collection", 
                        "museumobject_count": 727886, 
                        "source": "", 
                        "cis_id": null, 
                        "museumobject_image_count": 137552, 
                        "type": "", 
                        "slug": "pdp"
                    }
                }
            ], 
            "location": "Prints & Drawings Study Room, level C, case MB2D, shelf SH27, box T86", 
            "marks": "", 
            "latitude": "51.88031000", 
            "techniques": [
                {
                    "pk": 1026, 
                    "model": "collection.technique", 
                    "fields": {
                        "name": "watercolour drawing", 
                        "museumobject_count": 26423, 
                        "source": "", 
                        "cis_id": null, 
                        "museumobject_image_count": 20763, 
                        "type": "", 
                        "slug": "watercolour-drawing"
                    }
                }
            ], 
            "materials": [
                {
                    "pk": 222, 
                    "model": "collection.material", 
                    "fields": {
                        "name": "kaolinite", 
                        "museumobject_count": 162, 
                        "source": "cis_materials", 
                        "cis_id": "13815", 
                        "museumobject_image_count": 57, 
                        "type": "", 
                        "slug": "kaolinite"
                    }
                }
            ], 
            "edition_number": "", 
            "styles": [], 
            "inventory_set": [
                {
                    "pk": 862319, 
                    "model": "collection.inventory", 
                    "extras": {
                        "gallery_id": 1046
                    }, 
                    "fields": {
                        "box": "T86", 
                        "case": "MB2D", 
                        "inventory_number": 960715, 
                        "room": "LVLC", 
                        "part_name": "", 
                        "museum_number": "E.1113-1920", 
                        "museumobject": 727359, 
                        "shelf": "SH27", 
                        "site": "VA", 
                        "on_display": true, 
                        "status": "", 
                        "location": "Prints & Drawings Study Room, level C", 
                        "museum_number_token": "e11131920", 
                        "gallery": 1046
                    }
                }
            ], 
            "updated": null, 
            "galleries": [
                {
                    "pk": 1046, 
                    "model": "collection.gallery", 
                    "fields": {
                        "room_code": "LVLC", 
                        "site_name": "", 
                        "name": "Prints & Drawings Study Room, level C", 
                        "site_code": "VA", 
                        "museumobject_count": 130871, 
                        "source": "", 
                        "on_display": true, 
                        "cis_id": "THES49171", 
                        "museumobject_image_count": 26196, 
                        "type": "", 
                        "slug": "lvlc-va"
                    }
                }
            ], 
            "names": [
                {
                    "pk": 6607, 
                    "model": "collection.name", 
                    "fields": {
                        "death_date": null, 
                        "surname": "", 
                        "name": "Convent of the Poor Clares, Kenmare", 
                        "gender": null, 
                        "museumobject_count": 3, 
                        "death_year": null, 
                        "source": "object_production", 
                        "cis_id": "A10413", 
                        "museumobject_image_count": 1, 
                        "forename": "", 
                        "birth_date": null, 
                        "nationality": "", 
                        "type": "organisation", 
                        "slug": "convent-of-the-poor-clares-kenmare", 
                        "birth_year": null
                    }
                }
            ], 
            "placecontext_set": [
                {
                    "pk": 406537, 
                    "model": "collection.placecontext", 
                    "extras": {
                        "place_id": 1384
                    }, 
                    "fields": {
                        "part_name": "", 
                        "uncertainty": "", 
                        "museumobject": 727359, 
                        "role": "made", 
                        "place": 1384, 
                        "order": 1
                    }
                }
            ], 
            "original_currency": "", 
            "museum_number_token": "e11131920", 
            "object": "Lace design", 
            "categories": [
                {
                    "pk": 23, 
                    "model": "collection.category", 
                    "fields": {
                        "name": "Textiles", 
                        "museumobject_count": 49001, 
                        "source": "cis_category", 
                        "cis_id": null, 
                        "museumobject_image_count": 10808, 
                        "type": "", 
                        "slug": "textiles"
                    }
                }, 
                {
                    "pk": 96, 
                    "model": "collection.category", 
                    "fields": {
                        "name": "Lace", 
                        "museumobject_count": 2241, 
                        "source": "cis_category", 
                        "cis_id": null, 
                        "museumobject_image_count": 602, 
                        "type": "", 
                        "slug": "lace"
                    }
                }
            ], 
            "last_checked": "2014-04-26 18:56:33", 
            "public_access_description": "", 
            "exhibition_history": "", 
            "bibliography": "John Murdoch and Susan Lambert, <u>Summary Catalogue of Textile Designs 1840-1985 in the V. & A. Museum and colour microfiche</u>, Surrey: Emmett Microform, 1986\nThe full text of the record is as follows:\n\n'ANON\n\nLace. Ireland. c. 1888\nDesign for needlepoint lace\nchinese white. 10.3 x 34.6 cm\nManufactured by Convent of Poor Clares, Kenmare.\nE 1113-1920\nFiche 23/A12'", 
            "vanda_exhibition_history": "", 
            "slug": "lace-design-convent-of-the", 
            "sys_updated": "2013-08-24 00:00:00", 
            "image_set": [], 
            "places": [
                {
                    "pk": 1384, 
                    "model": "collection.place", 
                    "extras": {
                        "parent_id": 4351
                    }, 
                    "fields": {
                        "name": "Kenmare", 
                        "parent": 4351, 
                        "country": "", 
                        "museumobject_count": 3, 
                        "longitude": "-9.58384000", 
                        "source": "production", 
                        "cis_id": "x37247", 
                        "museumobject_image_count": 1, 
                        "latitude": "51.88031000", 
                        "type": "city/town", 
                        "slug": "kenmare-x37247"
                    }
                }
            ], 
            "artist": "Convent of the Poor Clares, Kenmare", 
            "namecontext_set": [
                {
                    "pk": 528439, 
                    "model": "collection.namecontext", 
                    "extras": {
                        "name_id": 6607
                    }, 
                    "fields": {
                        "name": 6607, 
                        "part_name": "", 
                        "uncertainty": "", 
                        "museumobject": 727359, 
                        "role": "makers", 
                        "order": 101
                    }
                }
            ], 
            "historical_significance": "", 
            "year_end": 1892, 
            "object_number": "O823046", 
            "events": [], 
            "credit": "", 
            "history_note": "", 
            "place": "Kenmare", 
            "production_note": "", 
            "historical_context_note": "", 
            "collection_code": "PDP"
        }
    }
]