[
    {
        "pk": 86882, 
        "model": "collection.museumobject", 
        "fields": {
            "original_price": "", 
            "attributions_note": "", 
            "related_museum_numbers": "", 
            "museum_number": "E.324-2005", 
            "date_end": "2008-12-31", 
            "labels": [], 
            "descriptive_line": "Sticker by ESM artificial, Canada, ca. 2004.", 
            "shape": "", 
            "longitude": null, 
            "year_start": 1999, 
            "exhibitions": [
                {
                    "pk": 3126, 
                    "model": "collection.exhibition", 
                    "fields": {
                        "va": true, 
                        "venue_id": null, 
                        "year_start": null, 
                        "name": "Street Art", 
                        "date_end": null, 
                        "museumobject_count": 69, 
                        "venue": "", 
                        "date_start": null, 
                        "year_end": null, 
                        "source": "", 
                        "cis_id": null, 
                        "museumobject_image_count": 58, 
                        "type": "", 
                        "slug": "street-art", 
                        "date_text": ""
                    }
                }, 
                {
                    "pk": 6771, 
                    "model": "collection.exhibition", 
                    "fields": {
                        "va": false, 
                        "venue_id": null, 
                        "year_start": null, 
                        "name": "Summer of Art - Urban Takeover", 
                        "date_end": null, 
                        "museumobject_count": 30, 
                        "venue": "", 
                        "date_start": null, 
                        "year_end": null, 
                        "source": "", 
                        "cis_id": null, 
                        "museumobject_image_count": 22, 
                        "type": "", 
                        "slug": "summer-of-art-urban-takeover", 
                        "date_text": ""
                    }
                }
            ], 
            "subjects": [
                {
                    "pk": 49097, 
                    "model": "collection.subject", 
                    "fields": {
                        "name": "cameras", 
                        "museumobject_count": 21, 
                        "source": "other", 
                        "cis_id": null, 
                        "museumobject_image_count": 10, 
                        "type": "", 
                        "slug": "cameras"
                    }
                }, 
                {
                    "pk": 53269, 
                    "model": "collection.subject", 
                    "fields": {
                        "name": "Jones, Davy", 
                        "museumobject_count": 1, 
                        "source": "name", 
                        "cis_id": "N4592", 
                        "museumobject_image_count": 1, 
                        "type": "", 
                        "slug": "jones-davy"
                    }
                }
            ], 
            "date_text": "ca. 2004 (made)", 
            "primary_image_id": "", 
            "rights": 2, 
            "physical_description": "A sticker showing Davy Jones of the Monkees taking a photograph. The background is bright green and the image is in shades of green and blue.", 
            "dimensions": "Height: 9.9 cm, Width: 6.4 cm", 
            "title": "", 
            "date_start": "1999-01-01", 
            "materials_techniques": "Digitally printed sticker", 
            "last_processed": "2014-04-01 00:30:28", 
            "label": "", 
            "event_text": "", 
            "production_type": "", 
            "collections": [
                {
                    "pk": 1, 
                    "model": "collection.collection", 
                    "fields": {
                        "code": "PDP", 
                        "name": "Prints, Drawings and Paintings Collection", 
                        "museumobject_count": 726097, 
                        "source": "", 
                        "cis_id": null, 
                        "museumobject_image_count": 137404, 
                        "type": "", 
                        "slug": "pdp"
                    }
                }
            ], 
            "location": "Prints & Drawings Study Room, level C, case TECHS", 
            "marks": "ESM / HAPPY WHEN / YOU'RE HAPPY", 
            "latitude": null, 
            "techniques": [], 
            "materials": [], 
            "edition_number": "", 
            "styles": [], 
            "inventory_set": [
                {
                    "pk": 147778, 
                    "model": "collection.inventory", 
                    "extras": {
                        "gallery_id": 1046
                    }, 
                    "fields": {
                        "box": "", 
                        "case": "TECHS", 
                        "inventory_number": 727801, 
                        "room": "LVLC", 
                        "part_name": "", 
                        "museum_number": "E.324-2005", 
                        "museumobject": 86882, 
                        "shelf": "", 
                        "site": "", 
                        "on_display": true, 
                        "status": "", 
                        "location": "Prints & Drawings Study Room, level C", 
                        "museum_number_token": "e3242005", 
                        "gallery": 1046
                    }
                }
            ], 
            "updated": null, 
            "galleries": [
                {
                    "pk": 1046, 
                    "model": "collection.gallery", 
                    "fields": {
                        "room_code": "LVLC", 
                        "site_name": "", 
                        "name": "Prints & Drawings Study Room, level C", 
                        "site_code": "VA", 
                        "museumobject_count": 130892, 
                        "source": "", 
                        "on_display": true, 
                        "cis_id": "THES49171", 
                        "museumobject_image_count": 26144, 
                        "type": "", 
                        "slug": "lvlc-va"
                    }
                }
            ], 
            "names": [
                {
                    "pk": 65599, 
                    "model": "collection.name", 
                    "fields": {
                        "death_date": null, 
                        "surname": "", 
                        "name": "ESM artificial", 
                        "gender": null, 
                        "museumobject_count": 1, 
                        "death_year": null, 
                        "source": "", 
                        "cis_id": "A14626", 
                        "museumobject_image_count": 1, 
                        "forename": "", 
                        "birth_date": null, 
                        "nationality": "", 
                        "type": "person", 
                        "slug": "esm", 
                        "birth_year": null
                    }
                }, 
                {
                    "pk": 72374, 
                    "model": "collection.name", 
                    "fields": {
                        "death_date": null, 
                        "surname": "", 
                        "name": "Jones, Davy", 
                        "gender": null, 
                        "museumobject_count": 1, 
                        "death_year": null, 
                        "source": "", 
                        "cis_id": "N4592", 
                        "museumobject_image_count": 1, 
                        "forename": "", 
                        "birth_date": null, 
                        "nationality": "", 
                        "type": "person", 
                        "slug": "jones-davy-n4592", 
                        "birth_year": null
                    }
                }
            ], 
            "placecontext_set": [
                {
                    "pk": 83386, 
                    "model": "collection.placecontext", 
                    "extras": {
                        "place_id": 205
                    }, 
                    "fields": {
                        "part_name": "", 
                        "uncertainty": "", 
                        "museumobject": 86882, 
                        "role": "made", 
                        "place": 205, 
                        "order": 1
                    }
                }
            ], 
            "original_currency": "", 
            "museum_number_token": "e3242005", 
            "object": "Print", 
            "categories": [
                {
                    "pk": 20, 
                    "model": "collection.category", 
                    "fields": {
                        "name": "Prints", 
                        "museumobject_count": 125512, 
                        "source": "cis_category", 
                        "cis_id": null, 
                        "museumobject_image_count": 28613, 
                        "type": "", 
                        "slug": "prints"
                    }
                }, 
                {
                    "pk": 1687, 
                    "model": "collection.category", 
                    "fields": {
                        "name": "Psychedelia", 
                        "museumobject_count": 36, 
                        "source": "cis_category", 
                        "cis_id": null, 
                        "museumobject_image_count": 8, 
                        "type": "", 
                        "slug": "psychedelia"
                    }
                }
            ], 
            "last_checked": "2014-04-01 00:30:28", 
            "public_access_description": "This sticker is by a US street artist called ESM, and it shows Davy Jones, singer with the American band The Monkees, smiling and pointing the camera at the viewer. It plays on a familiar image; the big grin and the slogan \u2018Happy when you\u2019re happy\u2019 nod to retro irony. Contemporary sticker ephemera often utilises familiar images of pop and film stars, politicians and cult figures. \n\nStickers like these are a part of the street art phenomenon, usually stuck on walls alongside stencil work and tag graffiti in urban areas. The simplicity and cheapness of the medium makes it attractive for young artists, and stickers crop up not only in graffiti sites but on buses and tube trains. Twenty-first-century psychedelia, demented cartoon characters, recycled film stars and a wild variety of visual references come together in a visual riot.", 
            "exhibition_history": "Summer of Art - Urban Takeover (Hannah's at Seale Hayne, Newton Abbot, Devon 14 June 2013-26 August 2013)\nStreet Art (Herbert Art Gallery 09/10/2010-16/01/2011)", 
            "bibliography": "", 
            "vanda_exhibition_history": "", 
            "slug": "print-esm-artificial", 
            "sys_updated": "2013-10-10 00:00:00", 
            "image_set": [], 
            "places": [
                {
                    "pk": 205, 
                    "model": "collection.place", 
                    "extras": {
                        "parent_id": 1178
                    }, 
                    "fields": {
                        "name": "Canada", 
                        "parent": 1178, 
                        "country": "", 
                        "museumobject_count": 1262, 
                        "longitude": null, 
                        "source": "production", 
                        "cis_id": "x30038", 
                        "museumobject_image_count": 42, 
                        "latitude": null, 
                        "type": "country", 
                        "slug": "canada-x30038"
                    }
                }
            ], 
            "artist": "ESM artificial", 
            "namecontext_set": [
                {
                    "pk": 102786, 
                    "model": "collection.namecontext", 
                    "extras": {
                        "name_id": 65599
                    }, 
                    "fields": {
                        "name": 65599, 
                        "part_name": "", 
                        "uncertainty": "", 
                        "museumobject": 86882, 
                        "role": "artist", 
                        "order": 1
                    }
                }, 
                {
                    "pk": 102787, 
                    "model": "collection.namecontext", 
                    "extras": {
                        "name_id": 72374
                    }, 
                    "fields": {
                        "name": 72374, 
                        "part_name": "", 
                        "uncertainty": "", 
                        "museumobject": 86882, 
                        "role": "subject", 
                        "order": 601
                    }
                }
            ], 
            "historical_significance": "", 
            "year_end": 2008, 
            "object_number": "O112415", 
            "events": [], 
            "credit": "Given by Riikka Kuittinen", 
            "history_note": "Displayed in the Link Corridor in Aug-Oct 2005 in the 'Street Art' display.", 
            "place": "Canada", 
            "production_note": "", 
            "historical_context_note": "", 
            "collection_code": "PDP"
        }
    }
]